README.rst
setup.cfg
setup.py
django_email_blacklist/__init__.py
django_email_blacklist.egg-info/PKG-INFO
django_email_blacklist.egg-info/SOURCES.txt
django_email_blacklist.egg-info/dependency_links.txt
django_email_blacklist.egg-info/top_level.txt