Metadata-Version: 1.1
Name: django-email-blacklist
Version: 1.0.1
Summary: Python class for use with Django to detect Disposable Emails.
Home-page: https://github.com/Zeioth/django-email-blacklist
Author: Zeioth
Author-email: test@gmail.com
License: MIT
Keywords: django email blacklist disposable validation
Platform: UNKNOWN
Classifier: Development Status :: 5 - Production/Stable
Classifier: Intended Audience :: Developers
Classifier: License :: OSI Approved :: MIT License
Classifier: Operating System :: OS Independent
Classifier: Programming Language :: Python
Classifier: Programming Language :: Python :: 3 :: Only
